{
  "info": {
    "_postman_id": "c462736c-116d-49e6-ac02-bbe237f5b84c",
    "name": "PH-Healthcare",
    "schema": "https://schema.getpostman.com/json/collection/v2.1.0/collection.json",
    "_exporter_id": "20639051"
  },
  "item": [
    {
      "name": "Auth",
      "item": [
        {
          "name": "Login",
          "request": {
            "method": "POST",
            "header": [],
            "body": {
              "mode": "raw",
              "raw": "{\r\n    \"email\": \"super.admin@admin.com\",\r\n    \"password\": \"123456\"\r\n}",
              "options": {
                "raw": {
                  "language": "json"
                }
              }
            },
            "url": {
              "raw": "http://localhost:5000/api/v1/auth/login",
              "protocol": "http",
              "host": ["localhost"],
              "port": "5000",
              "path": ["api", "v1", "auth", "login"]
            }
          },
          "response": []
        },
        {
          "name": "refresh-token",
          "request": {
            "method": "POST",
            "header": [],
            "url": {
              "raw": "http://localhost:5000/api/v1/auth/refresh-token",
              "protocol": "http",
              "host": ["localhost"],
              "port": "5000",
              "path": ["api", "v1", "auth", "refresh-token"]
            }
          },
          "response": []
        },
        {
          "name": "change-password",
          "request": {
            "method": "PATCH",
            "header": [
              {
                "key": "Authorization",
                "value": "eyJhbGciOiJIUzI1NiIsInR5cCI6IkpXVCJ9.eyJlbWFpbCI6ImFkbWluMUBob3RtYWlsLmNvbSIsInJvbGUiOiJQQVRJRU5UIiwiaWF0IjoxNzExMzgxNjMwLCJleHAiOjE3MTE0NjgwMzB9.3KchOYk0yZAY-hTzorrWB8ONm_PmhqDft5YIjKxG3Y0",
                "type": "text"
              }
            ],
            "body": {
              "mode": "raw",
              "raw": "{\r\n    \"oldPassword\": \"newpassword\",\r\n    \"newPassword\": \"newpassword1\"\r\n}",
              "options": {
                "raw": {
                  "language": "json"
                }
              }
            },
            "url": {
              "raw": "http://localhost:5000/api/v1/auth/change-password",
              "protocol": "http",
              "host": ["localhost"],
              "port": "5000",
              "path": ["api", "v1", "auth", "change-password"]
            }
          },
          "response": []
        },
        {
          "name": "forgot-password",
          "request": {
            "method": "POST",
            "header": [],
            "body": {
              "mode": "raw",
              "raw": "{\r\n    \"email\": \"usadadu09@gmail.com\"\r\n}",
              "options": {
                "raw": {
                  "language": "json"
                }
              }
            },
            "url": {
              "raw": "http://localhost:5000/api/v1/auth/forgot-password",
              "protocol": "http",
              "host": ["localhost"],
              "port": "5000",
              "path": ["api", "v1", "auth", "forgot-password"]
            }
          },
          "response": []
        },
        {
          "name": "reset-password",
          "request": {
            "method": "POST",
            "header": [
              {
                "key": "Authorization",
                "value": "eyJhbGciOiJIUzI1NiIsInR5cCI6IkpXVCJ9.eyJpZCI6IjMyZGY1N2Y3LTIzMTMtNGViMS05NGE1LWQ2M2ViMDU3M2Q0YyIsImVtYWlsIjoidXNhZGFkdTA5QGdtYWlsLmNvbSIsImlhdCI6MTcxMTM5OTE1NSwiZXhwIjoxNzExMzk5NDU1fQ.lMfB-MS9lGv_X_gbB20Ke2rniLME_5uRt-HZ0XdCADg",
                "type": "text"
              }
            ],
            "body": {
              "mode": "raw",
              "raw": "{\r\n \r\n    \"id\": \"32df57f7-2313-4eb1-94a5-d63eb0573d4c\",\r\n    \"password\": \"newpassword\"\r\n \r\n}",
              "options": {
                "raw": {
                  "language": "json"
                }
              }
            },
            "url": {
              "raw": "http://localhost:5000/api/v1/auth/reset-password",
              "protocol": "http",
              "host": ["localhost"],
              "port": "5000",
              "path": ["api", "v1", "auth", "reset-password"]
            }
          },
          "response": []
        }
      ]
    },
    {
      "name": "User",
      "item": [
        {
          "name": "Create Admin",
          "request": {
            "method": "POST",
            "header": [
              {
                "key": "Authorization",
                "value": "eyJhbGciOiJIUzI1NiIsInR5cCI6IkpXVCJ9.eyJ1c2VySWQiOiIwNzhhYjQ2OC01MTNlLTQ5MjUtYjgyYS05YWI3M2I4ZThlZmQiLCJyb2xlIjoiU1VQRVJfQURNSU4iLCJlbWFpbCI6InN1cGVyLmFkbWluQGFkbWluLmNvbSIsImlhdCI6MTczNzQ0MTk5NSwiZXhwIjoxNzM3NTI4Mzk1fQ.AuccbLw0fw7Wgjqy9iR3orfX7R2onjKTgT9SmCb7_Xs",
                "type": "text"
              }
            ],
            "body": {
              "mode": "formdata",
              "formdata": [
                {
                  "key": "file",
                  "type": "file",
                  "src": "/I:/Model/model-1.png"
                },
                {
                  "key": "data",
                  "value": "{\n    \"password\": \"newpassword\",\n    \"admin\": {\n        \"email\": \"cloud@admin.com\",\n        \"name\": \"James Bond\",\n\"contactNumber\":\"0191928181\"\n    }\n}",
                  "type": "text"
                }
              ]
            },
            "url": {
              "raw": "http://localhost:5000/api/v1/user/create-admin",
              "protocol": "http",
              "host": ["localhost"],
              "port": "5000",
              "path": ["api", "v1", "user", "create-admin"]
            }
          },
          "response": []
        },
        {
          "name": "Create Doctor",
          "request": {
            "method": "POST",
            "header": [
              {
                "key": "Authorization",
                "value": "{{superAdmin}}",
                "type": "text"
              }
            ],
            "body": {
              "mode": "formdata",
              "formdata": [
                {
                  "key": "file",
                  "type": "file",
                  "src": "/I:/Model/model-25.png"
                },
                {
                  "key": "data",
                  "value": "{\n  \"password\": \"123456\",\n  \"doctor\": {\n    \"email\": \"doctor56@gmail.com\",\n    \"name\": \"Dr. John Doe\",\n    \"contactNumber\": \"+9876543210\",\n    \"city\": \"Dhaka\",\n    \"address\": \"456 Health Avenue, Metropolis\",\n    \"registrationNumber\": \"67890\",\n    \"experience\": 10,\n    \"gender\": \"FEMALE\",\n    \"apointmentFee\": 150,\n    \"qualification\": \"MBBS, FRCS\",\n    \"currentWorkingPlace\": \"Global Health Clinic\",\n    \"designation\": \"Chief Medical Officer\"\n  }\n}\n",
                  "type": "text"
                }
              ]
            },
            "url": {
              "raw": "http://localhost:5000/api/v1/user/create-doctor",
              "protocol": "http",
              "host": ["localhost"],
              "port": "5000",
              "path": ["api", "v1", "user", "create-doctor"]
            }
          },
          "response": []
        },
        {
          "name": "Create Patient",
          "request": {
            "method": "POST",
            "header": [
              {
                "key": "Authorization",
                "value": "{{adminToken}}",
                "type": "text"
              }
            ],
            "body": {
              "mode": "formdata",
              "formdata": [
                {
                  "key": "file",
                  "type": "file",
                  "src": "/I:/Model/model-6.png"
                },
                {
                  "key": "data",
                  "value": "{\n  \"password\": \"newpassword\",\n  \"patient\": {\n    \"name\": \"John\",\n    \"email\": \"john@example.com\",\n    \"contactNumber\": \"1234567890\",\n\"address\":\"Feni\"\n}\n}",
                  "type": "text"
                }
              ]
            },
            "url": {
              "raw": "http://localhost:5000/api/v1/user/create-patient",
              "protocol": "http",
              "host": ["localhost"],
              "port": "5000",
              "path": ["api", "v1", "user", "create-patient"]
            }
          },
          "response": []
        },
        {
          "name": "Get all users",
          "request": {
            "method": "GET",
            "header": [
              {
                "key": "Authorization",
                "value": "{{superAdmin}}",
                "type": "text"
              }
            ],
            "url": {
              "raw": "http://localhost:5000/api/v1/user",
              "protocol": "http",
              "host": ["localhost"],
              "port": "5000",
              "path": ["api", "v1", "user"]
            }
          },
          "response": []
        },
        {
          "name": "Update status",
          "protocolProfileBehavior": {
            "disableBodyPruning": true
          },
          "request": {
            "method": "GET",
            "header": [],
            "body": {
              "mode": "raw",
              "raw": "",
              "options": {
                "raw": {
                  "language": "json"
                }
              }
            },
            "url": {
              "raw": ""
            }
          },
          "response": []
        },
        {
          "name": "Get My Profile",
          "request": {
            "method": "GET",
            "header": [
              {
                "key": "Authorization",
                "value": "{{superAdmin}}",
                "type": "text"
              }
            ],
            "url": {
              "raw": "http://localhost:5000/api/v1/user/me",
              "protocol": "http",
              "host": ["localhost"],
              "port": "5000",
              "path": ["api", "v1", "user", "me"]
            }
          },
          "response": []
        },
        {
          "name": "Update My Profile",
          "request": {
            "method": "PATCH",
            "header": [
              {
                "key": "Authorization",
                "value": "{{superAdmin}}",
                "type": "text"
              }
            ],
            "body": {
              "mode": "formdata",
              "formdata": [
                {
                  "key": "file",
                  "type": "file",
                  "src": "/I:/Model/model-2.png"
                },
                {
                  "key": "data",
                  "value": "{\"name\":\"Taleban\"}",
                  "type": "text"
                }
              ]
            },
            "url": {
              "raw": "http://localhost:5000/api/v1/user/update-my-profile",
              "protocol": "http",
              "host": ["localhost"],
              "port": "5000",
              "path": ["api", "v1", "user", "update-my-profile"]
            }
          },
          "response": []
        }
      ]
    },
    {
      "name": "Admin",
      "item": [
        {
          "name": "Get All Admin",
          "request": {
            "method": "GET",
            "header": [],
            "url": {
              "raw": "http://localhost:5000/api/v1/admin?sortBy=name&sortOrder=asc&page=6&limit=2",
              "protocol": "http",
              "host": ["localhost"],
              "port": "5000",
              "path": ["api", "v1", "admin"],
              "query": [
                {
                  "key": "searchTerm",
                  "value": "hot",
                  "disabled": true
                },
                {
                  "key": "isDeleted",
                  "value": "",
                  "disabled": true
                },
                {
                  "key": "sortBy",
                  "value": "name"
                },
                {
                  "key": "sortOrder",
                  "value": "asc"
                },
                {
                  "key": "page",
                  "value": "6"
                },
                {
                  "key": "limit",
                  "value": "2"
                }
              ]
            }
          },
          "response": []
        },
        {
          "name": "Get Single Admin",
          "request": {
            "method": "GET",
            "header": [],
            "url": {
              "raw": "http://localhost:5000/api/v1/admin/2b3a5981-5fd9-4f86-954f-997f388c2848",
              "protocol": "http",
              "host": ["localhost"],
              "port": "5000",
              "path": [
                "api",
                "v1",
                "admin",
                "2b3a5981-5fd9-4f86-954f-997f388c2848"
              ]
            }
          },
          "response": []
        },
        {
          "name": "Update admin",
          "request": {
            "method": "PATCH",
            "header": [],
            "body": {
              "mode": "raw",
              "raw": "{\r\n    \"name\": \"Will\"\r\n}",
              "options": {
                "raw": {
                  "language": "json"
                }
              }
            },
            "url": {
              "raw": "http://localhost:5000/api/v1/admin/2b3a5981-5fd9-4f86-954f-997f388c2848",
              "protocol": "http",
              "host": ["localhost"],
              "port": "5000",
              "path": [
                "api",
                "v1",
                "admin",
                "2b3a5981-5fd9-4f86-954f-997f388c2848"
              ]
            }
          },
          "response": []
        },
        {
          "name": "Delete Admin",
          "request": {
            "method": "DELETE",
            "header": [],
            "url": {
              "raw": "http://localhost:5000/api/v1/admin/573eadff-94a5-4649-b096-455217494eba",
              "protocol": "http",
              "host": ["localhost"],
              "port": "5000",
              "path": [
                "api",
                "v1",
                "admin",
                "573eadff-94a5-4649-b096-455217494eba"
              ]
            }
          },
          "response": []
        },
        {
          "name": "Soft Delete",
          "request": {
            "method": "DELETE",
            "header": [],
            "url": {
              "raw": "http://localhost:5000/api/v1/admin/573eadff-94a5-4649-b096-455217494eba",
              "protocol": "http",
              "host": ["localhost"],
              "port": "5000",
              "path": [
                "api",
                "v1",
                "admin",
                "573eadff-94a5-4649-b096-455217494eba"
              ]
            }
          },
          "response": []
        }
      ]
    },
    {
      "name": "Doctor",
      "item": [
        {
          "name": "Get All Doctor",
          "request": {
            "method": "GET",
            "header": [
              {
                "key": "Authorization",
                "value": "eyJhbGciOiJIUzI1NiIsInR5cCI6IkpXVCJ9.eyJlbWFpbCI6ImNsb3VkQGFkbWluLmNvbSIsInJvbGUiOiJTVVBFUl9BRE1JTiIsImlhdCI6MTcxMjU2MjIzMCwiZXhwIjoxNzEyODIxNDMwfQ.qGdTyVnDhLGmctK0DN1W6E8m23W83tm_QVshxgfvHf0",
                "type": "text"
              }
            ],
            "url": {
              "raw": "http://localhost:5000/api/v1/doctor",
              "protocol": "http",
              "host": ["localhost"],
              "port": "5000",
              "path": ["api", "v1", "doctor"],
              "query": [
                {
                  "key": "sortBy",
                  "value": "name",
                  "disabled": true
                },
                {
                  "key": "sortOrder",
                  "value": "asc",
                  "disabled": true
                },
                {
                  "key": "page",
                  "value": "6",
                  "disabled": true
                },
                {
                  "key": "limit",
                  "value": "2",
                  "disabled": true
                },
                {
                  "key": "searchTerm",
                  "value": "hot",
                  "disabled": true
                },
                {
                  "key": "isDeleted",
                  "value": "",
                  "disabled": true
                },
                {
                  "key": "city",
                  "value": "Dhaka",
                  "disabled": true
                }
              ]
            }
          },
          "response": []
        },
        {
          "name": "Get Single Doctor",
          "request": {
            "method": "GET",
            "header": [
              {
                "key": "Authorization",
                "value": "eyJhbGciOiJIUzI1NiIsInR5cCI6IkpXVCJ9.eyJlbWFpbCI6ImNsb3VkQGFkbWluLmNvbSIsInJvbGUiOiJTVVBFUl9BRE1JTiIsImlhdCI6MTcxMjU2MjIzMCwiZXhwIjoxNzEyODIxNDMwfQ.qGdTyVnDhLGmctK0DN1W6E8m23W83tm_QVshxgfvHf0",
                "type": "text"
              }
            ],
            "url": {
              "raw": "http://localhost:5000/api/v1/admin/2b3a5981-5fd9-4f86-954f-997f388c2848",
              "protocol": "http",
              "host": ["localhost"],
              "port": "5000",
              "path": [
                "api",
                "v1",
                "admin",
                "2b3a5981-5fd9-4f86-954f-997f388c2848"
              ]
            }
          },
          "response": []
        },
        {
          "name": "Update Doctor",
          "request": {
            "method": "PATCH",
            "header": [
              {
                "key": "Authorization",
                "value": "eyJhbGciOiJIUzI1NiIsInR5cCI6IkpXVCJ9.eyJlbWFpbCI6ImNsb3VkQGFkbWluLmNvbSIsInJvbGUiOiJTVVBFUl9BRE1JTiIsImlhdCI6MTcxMjU2MjIzMCwiZXhwIjoxNzEyODIxNDMwfQ.qGdTyVnDhLGmctK0DN1W6E8m23W83tm_QVshxgfvHf0",
                "type": "text"
              }
            ],
            "body": {
              "mode": "raw",
              "raw": "{\r\n    \"specialties\": [\r\n        {\r\n            \"specialtiesId\": \"df3e69ae-b4da-4ca8-8561-6a7886cbe43d\",\r\n            \"isDeleted\": false\r\n        }\r\n    ]\r\n}",
              "options": {
                "raw": {
                  "language": "json"
                }
              }
            },
            "url": {
              "raw": "http://localhost:5000/api/v1/doctor/46059fef-fbcf-4ff6-8e79-a2f29616b4c5",
              "protocol": "http",
              "host": ["localhost"],
              "port": "5000",
              "path": [
                "api",
                "v1",
                "doctor",
                "46059fef-fbcf-4ff6-8e79-a2f29616b4c5"
              ]
            }
          },
          "response": []
        },
        {
          "name": "Delete Doctor",
          "request": {
            "method": "DELETE",
            "header": [
              {
                "key": "Authorization",
                "value": "eyJhbGciOiJIUzI1NiIsInR5cCI6IkpXVCJ9.eyJlbWFpbCI6ImNsb3VkQGFkbWluLmNvbSIsInJvbGUiOiJTVVBFUl9BRE1JTiIsImlhdCI6MTcxMjU2MjIzMCwiZXhwIjoxNzEyODIxNDMwfQ.qGdTyVnDhLGmctK0DN1W6E8m23W83tm_QVshxgfvHf0",
                "type": "text"
              }
            ],
            "url": {
              "raw": "http://localhost:5000/api/v1/doctor/573eadff-94a5-4649-b096-455217494eba",
              "protocol": "http",
              "host": ["localhost"],
              "port": "5000",
              "path": [
                "api",
                "v1",
                "doctor",
                "573eadff-94a5-4649-b096-455217494eba"
              ]
            }
          },
          "response": []
        },
        {
          "name": "Soft Delete",
          "request": {
            "method": "DELETE",
            "header": [
              {
                "key": "Authorization",
                "value": "eyJhbGciOiJIUzI1NiIsInR5cCI6IkpXVCJ9.eyJlbWFpbCI6ImNsb3VkQGFkbWluLmNvbSIsInJvbGUiOiJTVVBFUl9BRE1JTiIsImlhdCI6MTcxMjU2MjIzMCwiZXhwIjoxNzEyODIxNDMwfQ.qGdTyVnDhLGmctK0DN1W6E8m23W83tm_QVshxgfvHf0",
                "type": "text"
              }
            ],
            "url": {
              "raw": "http://localhost:5000/api/v1/doctor/573eadff-94a5-4649-b096-455217494eba",
              "protocol": "http",
              "host": ["localhost"],
              "port": "5000",
              "path": [
                "api",
                "v1",
                "doctor",
                "573eadff-94a5-4649-b096-455217494eba"
              ]
            }
          },
          "response": []
        }
      ]
    },
    {
      "name": "Patient",
      "item": [
        {
          "name": "Get All Patient",
          "request": {
            "method": "GET",
            "header": [
              {
                "key": "Authorization",
                "value": "{{adminToken}}",
                "type": "text"
              }
            ],
            "url": {
              "raw": "http://localhost:5000/api/v1/patient?sortBy=name",
              "protocol": "http",
              "host": ["localhost"],
              "port": "5000",
              "path": ["api", "v1", "patient"],
              "query": [
                {
                  "key": "searchTerm",
                  "value": "hot",
                  "disabled": true
                },
                {
                  "key": "isDeleted",
                  "value": "",
                  "disabled": true
                },
                {
                  "key": "sortBy",
                  "value": "name"
                },
                {
                  "key": "sortOrder",
                  "value": "asc",
                  "disabled": true
                },
                {
                  "key": "page",
                  "value": "6",
                  "disabled": true
                },
                {
                  "key": "limit",
                  "value": "2",
                  "disabled": true
                }
              ]
            }
          },
          "response": []
        },
        {
          "name": "Get Single Patient",
          "request": {
            "method": "GET",
            "header": [
              {
                "key": "Authorization",
                "value": "{{adminToken}}",
                "type": "text"
              }
            ],
            "url": {
              "raw": "http://localhost:5000/api/v1/patient/2b3a5981-5fd9-4f86-954f-997f388c2848",
              "protocol": "http",
              "host": ["localhost"],
              "port": "5000",
              "path": [
                "api",
                "v1",
                "patient",
                "2b3a5981-5fd9-4f86-954f-997f388c2848"
              ]
            }
          },
          "response": []
        },
        {
          "name": "Update Patient",
          "request": {
            "method": "PATCH",
            "header": [
              {
                "key": "Authorization",
                "value": "{{adminToken}}",
                "type": "text"
              }
            ],
            "body": {
              "mode": "raw",
              "raw": "{\r\n    \"name\": \"Williamson\",\r\n    \"patientHealthData\": {\r\n        \"gender\": \"MALE\",\r\n        \"dateOfBirth\": \"2 January 2003\",\r\n        \"bloodGroup\": \"O_NEGATIVE\",\r\n        \"height\": \"200cm\",\r\n        \"weight\": \"1000cm\"\r\n    },\r\n    \"medicalReport\": {\r\n        \"reportName\": \"New Medical Report2\",\r\n        \"reportLink\": \"New Report Link2\"\r\n    }\r\n}",
              "options": {
                "raw": {
                  "language": "json"
                }
              }
            },
            "url": {
              "raw": "http://localhost:5000/api/v1/patient/fd2d62c6-1784-41c6-8b67-dc6179c777e3",
              "protocol": "http",
              "host": ["localhost"],
              "port": "5000",
              "path": [
                "api",
                "v1",
                "patient",
                "fd2d62c6-1784-41c6-8b67-dc6179c777e3"
              ]
            }
          },
          "response": []
        },
        {
          "name": "Delete Patient",
          "request": {
            "method": "DELETE",
            "header": [
              {
                "key": "Authorization",
                "value": "{{adminToken}}",
                "type": "text"
              }
            ],
            "url": {
              "raw": "http://localhost:5000/api/v1/patient/c886c56a-1242-491f-8825-4b2e98e1a78e",
              "protocol": "http",
              "host": ["localhost"],
              "port": "5000",
              "path": [
                "api",
                "v1",
                "patient",
                "c886c56a-1242-491f-8825-4b2e98e1a78e"
              ]
            }
          },
          "response": []
        },
        {
          "name": "Soft Delete",
          "request": {
            "method": "DELETE",
            "header": [
              {
                "key": "Authorization",
                "value": "{{adminToken}}",
                "type": "text"
              }
            ],
            "url": {
              "raw": "http://localhost:5000/api/v1/patient/573eadff-94a5-4649-b096-455217494eba",
              "protocol": "http",
              "host": ["localhost"],
              "port": "5000",
              "path": [
                "api",
                "v1",
                "patient",
                "573eadff-94a5-4649-b096-455217494eba"
              ]
            }
          },
          "response": []
        }
      ]
    },
    {
      "name": "Specialties",
      "item": [
        {
          "name": "Create Specialties",
          "request": {
            "method": "POST",
            "header": [
              {
                "key": "Authorization",
                "value": "",
                "type": "text"
              }
            ],
            "body": {
              "mode": "formdata",
              "formdata": [
                {
                  "key": "data",
                  "value": "{\n    \"title\": \"Ophthalmologist\"\n}",
                  "type": "text"
                },
                {
                  "key": "file",
                  "type": "file",
                  "src": "/C:/Users/user/Desktop/Healthcare/healthcare-frontend/src/assets/svgs/Ophthalmology.svg"
                }
              ]
            },
            "url": {
              "raw": "http://localhost:5000/api/v1/specialties",
              "protocol": "http",
              "host": ["localhost"],
              "port": "5000",
              "path": ["api", "v1", "specialties"]
            }
          },
          "response": []
        },
        {
          "name": "Get All Specialties",
          "protocolProfileBehavior": {
            "disableBodyPruning": true
          },
          "request": {
            "method": "GET",
            "header": [
              {
                "key": "Authorization",
                "value": "eyJhbGciOiJIUzI1NiIsInR5cCI6IkpXVCJ9.eyJlbWFpbCI6ImNsb3VkQGFkbWluLmNvbSIsInJvbGUiOiJTVVBFUl9BRE1JTiIsImlhdCI6MTcxMjU2MjIzMCwiZXhwIjoxNzEyODIxNDMwfQ.qGdTyVnDhLGmctK0DN1W6E8m23W83tm_QVshxgfvHf0",
                "type": "text"
              }
            ],
            "body": {
              "mode": "formdata",
              "formdata": [
                {
                  "key": "data",
                  "value": "{\n    \"title\": \"Heart Special\"\n}",
                  "type": "text"
                },
                {
                  "key": "file",
                  "type": "file",
                  "src": "/C:/Users/Naimur Reza/Desktop/levi.jpg"
                }
              ]
            },
            "url": {
              "raw": "http://localhost:5000/api/v1/specialties",
              "protocol": "http",
              "host": ["localhost"],
              "port": "5000",
              "path": ["api", "v1", "specialties"]
            }
          },
          "response": []
        },
        {
          "name": "Delete Specialties",
          "request": {
            "method": "DELETE",
            "header": [
              {
                "key": "Authorization",
                "value": "eyJhbGciOiJIUzI1NiIsInR5cCI6IkpXVCJ9.eyJlbWFpbCI6ImNsb3VkQGFkbWluLmNvbSIsInJvbGUiOiJTVVBFUl9BRE1JTiIsImlhdCI6MTcxMjU2MjIzMCwiZXhwIjoxNzEyODIxNDMwfQ.qGdTyVnDhLGmctK0DN1W6E8m23W83tm_QVshxgfvHf0",
                "type": "text"
              }
            ],
            "body": {
              "mode": "formdata",
              "formdata": [
                {
                  "key": "data",
                  "value": "{\n    \"title\": \"Heart Special\"\n}",
                  "type": "text"
                },
                {
                  "key": "file",
                  "type": "file",
                  "src": "/C:/Users/Naimur Reza/Desktop/levi.jpg"
                }
              ]
            },
            "url": {
              "raw": "http://localhost:5000/api/v1/specialties/id",
              "protocol": "http",
              "host": ["localhost"],
              "port": "5000",
              "path": ["api", "v1", "specialties", "id"]
            }
          },
          "response": []
        }
      ]
    },
    {
      "name": "Schedules",
      "item": [
        {
          "name": "Create Schedule",
          "request": {
            "method": "POST",
            "header": [
              {
                "key": "Authorization",
                "value": "{{superAdmin}}",
                "type": "text"
              }
            ],
            "body": {
              "mode": "raw",
              "raw": "{\r\n    \"startDate\": \"2025-01-25\",\r\n    \"endDate\": \"2025-01-26\",\r\n    \"startTime\": \"09:00\",\r\n    \"endTime\": \"17:00\"\r\n}",
              "options": {
                "raw": {
                  "language": "json"
                }
              }
            },
            "url": {
              "raw": "http://localhost:5000/api/v1/schedule",
              "protocol": "http",
              "host": ["localhost"],
              "port": "5000",
              "path": ["api", "v1", "schedule"]
            }
          },
          "response": []
        },
        {
          "name": "Get All Schedules",
          "request": {
            "method": "GET",
            "header": [
              {
                "key": "Authorization",
                "value": "{{doctorToken}}",
                "type": "text"
              }
            ],
            "url": {
              "raw": "http://localhost:5000/api/v1/schedule?startDate=2024-06-27T03:30:00.000Z&endDate=2024-06-27T04:00:00.000Z",
              "protocol": "http",
              "host": ["localhost"],
              "port": "5000",
              "path": ["api", "v1", "schedule"],
              "query": [
                {
                  "key": "limit",
                  "value": "2",
                  "disabled": true
                },
                {
                  "key": "page",
                  "value": "7",
                  "disabled": true
                },
                {
                  "key": "startDate",
                  "value": "2024-06-27T03:30:00.000Z"
                },
                {
                  "key": "endDate",
                  "value": "2024-06-27T04:00:00.000Z"
                }
              ]
            }
          },
          "response": []
        }
      ]
    },
    {
      "name": "Doctor Schedules",
      "item": [
        {
          "name": "Create Doctor Schedule",
          "request": {
            "method": "POST",
            "header": [
              {
                "key": "Authorization",
                "value": "{{bantiDoctor}}",
                "type": "text"
              }
            ],
            "body": {
              "mode": "raw",
              "raw": "{\r\n    \"scheduleIds\": [\r\n        \"29c92f14-ef05-489b-a01d-d9389e9dc700\",\r\n        \"2bbb026a-db09-4f0a-bb81-c21ce53b150c\",\r\n        \"3b2f4de1-3048-4ad4-a225-70163a8186ef\",\r\n        \"3c20ff63-b0ca-48f9-ad25-b85a2a0b8319\",\r\n        \"3c25e6b7-b87a-4647-ab42-7b356a9232c8\",\r\n        \"4b2a8ed5-f49a-4b33-a370-2c5277d1e27f\"\r\n    ]\r\n}",
              "options": {
                "raw": {
                  "language": "json"
                }
              }
            },
            "url": {
              "raw": "http://localhost:5000/api/v1/doctor-schedule",
              "protocol": "http",
              "host": ["localhost"],
              "port": "5000",
              "path": ["api", "v1", "doctor-schedule"]
            }
          },
          "response": []
        },
        {
          "name": "Get All Doctor Schedules",
          "request": {
            "method": "GET",
            "header": [
              {
                "key": "Authorization",
                "value": "{{doctorToken}}",
                "type": "text"
              }
            ],
            "url": {
              "raw": "http://localhost:5000/api/v1/schedule?startDate=2024-06-27T03:30:00.000Z&endDate=2024-06-27T04:00:00.000Z",
              "protocol": "http",
              "host": ["localhost"],
              "port": "5000",
              "path": ["api", "v1", "schedule"],
              "query": [
                {
                  "key": "limit",
                  "value": "2",
                  "disabled": true
                },
                {
                  "key": "page",
                  "value": "7",
                  "disabled": true
                },
                {
                  "key": "startDate",
                  "value": "2024-06-27T03:30:00.000Z"
                },
                {
                  "key": "endDate",
                  "value": "2024-06-27T04:00:00.000Z"
                }
              ]
            }
          },
          "response": []
        },
        {
          "name": "Create Doctor Schedule Copy",
          "protocolProfileBehavior": {
            "disableBodyPruning": true
          },
          "request": {
            "method": "GET",
            "header": [
              {
                "key": "Authorization",
                "value": "{{doctorToken}}",
                "type": "text",
                "disabled": true
              }
            ],
            "body": {
              "mode": "raw",
              "raw": "{\r\n    \"scheduleIds\": [\r\n        \"11e37c24-3b19-4060-827c-d8e66ef18015\",\r\n        \"12d3048d-3b62-46bc-a8a4-86f93e430e6e\",\r\n        \"1bb9e0b8-007a-4aa9-92a2-ee4230bbe357\"\r\n    ]\r\n}",
              "options": {
                "raw": {
                  "language": "json"
                }
              }
            },
            "url": {
              "raw": "http://localhost:5000/api/v1/doctor-schedule/my-schedule?isBooked=false",
              "protocol": "http",
              "host": ["localhost"],
              "port": "5000",
              "path": ["api", "v1", "doctor-schedule", "my-schedule"],
              "query": [
                {
                  "key": "isBooked",
                  "value": "false"
                }
              ]
            }
          },
          "response": []
        }
      ]
    },
    {
      "name": "Appointment",
      "item": [
        {
          "name": "Book Appointment",
          "request": {
            "method": "POST",
            "header": [
              {
                "key": "Authorization",
                "value": "{{johnPatient}}",
                "type": "text"
              }
            ],
            "body": {
              "mode": "raw",
              "raw": "{\r\n    \"doctorId\": \"aaac2247-10f6-4f3f-a6e4-271274814b96\",\r\n    \"scheduleId\": \"4b2a8ed5-f49a-4b33-a370-2c5277d1e27f\"\r\n}",
              "options": {
                "raw": {
                  "language": "json"
                }
              }
            },
            "url": {
              "raw": "http://localhost:5000/api/v1/appointment",
              "protocol": "http",
              "host": ["localhost"],
              "port": "5000",
              "path": ["api", "v1", "appointment"]
            }
          },
          "response": []
        }
      ]
    },
    {
      "name": "Payments",
      "item": [
        {
          "name": "New Request",
          "request": {
            "method": "POST",
            "header": [
              {
                "key": "Authorization",
                "value": "{{patient_token}}",
                "type": "text"
              }
            ],
            "url": {
              "raw": "http://localhost:5000/api/v1/payments",
              "protocol": "http",
              "host": ["localhost"],
              "port": "5000",
              "path": ["api", "v1", "payments"],
              "query": [
                {
                  "key": "",
                  "value": null,
                  "disabled": true
                }
              ]
            }
          },
          "response": []
        }
      ]
    },
    {
      "name": "Notification",
      "item": [
        {
          "name": "Get My Notifications",
          "request": {
            "method": "GET",
            "header": [
              {
                "key": "Authorization",
                "value": "{{dhakaDoctorToken}}",
                "type": "text"
              }
            ],
            "url": {
              "raw": "http://localhost:5000/api/v1/notification/my-notifications",
              "protocol": "http",
              "host": ["localhost"],
              "port": "5000",
              "path": ["api", "v1", "notification", "my-notifications"]
            }
          },
          "response": []
        },
        {
          "name": "Get Single Notification",
          "request": {
            "method": "GET",
            "header": [
              {
                "key": "Authorization",
                "value": "{{dhakaDoctorToken}}",
                "type": "text"
              }
            ],
            "url": {
              "raw": "http://localhost:5000/api/v1/notification/my-notifications/52ee094d-90ba-4b32-9957-e50d8399141a",
              "protocol": "http",
              "host": ["localhost"],
              "port": "5000",
              "path": [
                "api",
                "v1",
                "notification",
                "my-notifications",
                "52ee094d-90ba-4b32-9957-e50d8399141a"
              ]
            }
          },
          "response": []
        },
        {
          "name": "Delete Notification",
          "request": {
            "method": "DELETE",
            "header": [
              {
                "key": "Authorization",
                "value": "{{hamPatient}}",
                "type": "text"
              }
            ],
            "url": {
              "raw": "http://localhost:5000/api/v1/notification/delete-notification/1e13f115-724a-4e1d-8a14-4e2260233004",
              "protocol": "http",
              "host": ["localhost"],
              "port": "5000",
              "path": [
                "api",
                "v1",
                "notification",
                "delete-notification",
                "1e13f115-724a-4e1d-8a14-4e2260233004"
              ]
            }
          },
          "response": []
        },
        {
          "name": "Toggle Read-Unread",
          "request": {
            "method": "PATCH",
            "header": [
              {
                "key": "Authorization",
                "value": "{{dhakaDoctorToken}}",
                "type": "text"
              }
            ],
            "url": {
              "raw": "http://localhost:5000/api/v1/notification/toggle-read-unread/52ee094d-90ba-4b32-9957-e50d8399141a",
              "protocol": "http",
              "host": ["localhost"],
              "port": "5000",
              "path": [
                "api",
                "v1",
                "notification",
                "toggle-read-unread",
                "52ee094d-90ba-4b32-9957-e50d8399141a"
              ]
            }
          },
          "response": []
        },
        {
          "name": "Create Notification",
          "request": {
            "method": "POST",
            "header": [
              {
                "key": "Authorization",
                "value": "{{superAdmin}}",
                "type": "text"
              }
            ],
            "body": {
              "mode": "raw",
              "raw": "{\r\n    \"title\": \"This is test notification from SuperAdmin\",\r\n    \"content\": \"this is test notification content from SuperAdmin. Do you get it?\"\r\n}",
              "options": {
                "raw": {
                  "language": "json"
                }
              }
            },
            "url": {
              "raw": "http://localhost:5000/api/v1/notification/send-notification",
              "protocol": "http",
              "host": ["localhost"],
              "port": "5000",
              "path": ["api", "v1", "notification", "send-notification"]
            }
          },
          "response": []
        }
      ]
    }
  ],
  "event": [
    {
      "listen": "prerequest",
      "script": {
        "type": "text/javascript",
        "packages": {},
        "exec": [""]
      }
    },
    {
      "listen": "test",
      "script": {
        "type": "text/javascript",
        "packages": {},
        "exec": [""]
      }
    }
  ],
  "variable": [
    {
      "key": "superAdmin",
      "value": "eyJhbGciOiJIUzI1NiIsInR5cCI6IkpXVCJ9.eyJ1c2VySWQiOiIwNzhhYjQ2OC01MTNlLTQ5MjUtYjgyYS05YWI3M2I4ZThlZmQiLCJyb2xlIjoiU1VQRVJfQURNSU4iLCJlbWFpbCI6InN1cGVyLmFkbWluQGFkbWluLmNvbSIsImlhdCI6MTczODA1OTUwOSwiZXhwIjoxNzQwNjUxNTA5fQ.BFDwhxlYLPNDdHOREmX-6y1ety5_SNao6EE97INAZ6g",
      "type": "string"
    },
    {
      "key": "dhakaDoctorToken",
      "value": "eyJhbGciOiJIUzI1NiIsInR5cCI6IkpXVCJ9.eyJ1c2VySWQiOiJhZDc5ZTZiMy1kOTFjLTQ0NjktODM3My0xYjUzYTU2OTMxYjAiLCJyb2xlIjoiRE9DVE9SIiwiZW1haWwiOiJkb2N0b3I1NkBnbWFpbC5jb20iLCJpYXQiOjE3Mzc1MjEwNTEsImV4cCI6MTc0MDExMzA1MX0.zAqi5COe8c1mT3nQFcPB3DDBQy_gZfrFw0xvPF0G4vk",
      "type": "string"
    },
    {
      "key": "bantiDoctor",
      "value": "eyJhbGciOiJIUzI1NiIsInR5cCI6IkpXVCJ9.eyJ1c2VySWQiOiI2MzA4ODg0OS02N2YyLTQ5M2YtYjE0Zi1lYjlhMTUwNjQxNTEiLCJyb2xlIjoiRE9DVE9SIiwiZW1haWwiOiJkb2N0b3IzNEBnbWFpbC5jb20iLCJpYXQiOjE3MzgwNDY2NjYsImV4cCI6MTc0MDYzODY2Nn0._B-3spHBXuM8zhuwI1ZEQTFTZEMXctxroDXyprca2H8",
      "type": "string"
    },
    {
      "key": "hamPatient",
      "value": "eyJhbGciOiJIUzI1NiIsInR5cCI6IkpXVCJ9.eyJ1c2VySWQiOiJkODQwODVkOC1jN2Y0LTRlNWUtYTVkOC03YTg4MjViNjgzNDUiLCJyb2xlIjoiUEFUSUVOVCIsImVtYWlsIjoiaGFtQGV4YW1wbGUuY29tIiwiaWF0IjoxNzM3NTQzMjkzLCJleHAiOjE3NDAxMzUyOTN9.GrndRZfbvv5_EHhofZ_tBIqW4o6pOQBoZCvv7iiCsZk",
      "type": "string"
    },
    {
      "key": "johnPatient",
      "value": "eyJhbGciOiJIUzI1NiIsInR5cCI6IkpXVCJ9.eyJ1c2VySWQiOiJmMzc4ZTFhOC0xZWVmLTQxMzUtODA3NS05ODZjNGFjNjllNjYiLCJyb2xlIjoiUEFUSUVOVCIsImVtYWlsIjoiam9obkBleGFtcGxlLmNvbSIsImlhdCI6MTczODA0NzIzNywiZXhwIjoxNzQwNjM5MjM3fQ.y7SYVdAJ1T50k4i9r5XU8crOBmbxpDKkGtbSjcINrzs",
      "type": "string"
    }
  ]
}
